cbor_json/__init__.py
cbor_json/_cbor_json_codecs.py
cbor_json/_custom_objects_base.py
cbor_json/custom_objects.py
cbor_json-0.1.0.dist-info/WHEEL
cbor_json-0.1.0.dist-info/LICENSE.txt
cbor_json-0.1.0.dist-info/METADATA
cbor_json-0.1.0.dist-info/RECORD
