Metadata-Version: 2.1
Name: cbor-json
Version: 0.1.0
Summary: Three-way conversion between 'native' Python data representation, CBOR, and JSON
Home-page: https://github.com/amaslyaev/cbor-json/
License: MIT
Author: Alexander Maslyeav
Author-email: maslyaev@gmail.com
Requires-Python: >=3.10
Classifier: Development Status :: 4 - Beta
Classifier: Intended Audience :: Developers
Classifier: License :: OSI Approved :: MIT License
Classifier: Programming Language :: Python :: 3
Classifier: Programming Language :: Python :: 3.10
Classifier: Programming Language :: Python :: 3.11
Classifier: Programming Language :: Python :: 3
Classifier: Topic :: Software Development :: Libraries :: Python Modules
Requires-Dist: base58 (>=2.1.1,<3.0.0)
Requires-Dist: cbor2 (>=5.4.0)
Project-URL: Repository, https://github.com/amaslyaev/cbor-json/
